MANIFEST.in
README.rst
setup.py
docs/HISTORY.txt
docs/LICENSE.GPL
docs/LICENSE.txt
ftw/__init__.py
ftw.events.egg-info/PKG-INFO
ftw.events.egg-info/SOURCES.txt
ftw.events.egg-info/dependency_links.txt
ftw.events.egg-info/entry_points.txt
ftw.events.egg-info/namespace_packages.txt
ftw.events.egg-info/not-zip-safe
ftw.events.egg-info/requires.txt
ftw.events.egg-info/top_level.txt
ftw/events/__init__.py
ftw/events/configure.zcml
ftw/events/hooks.py
ftw/events/interfaces.py
ftw/events/lawgiver.zcml
ftw/events/permissions.zcml
ftw/events/profiles.zcml
ftw/events/resources.zcml
ftw/events/syndication.py
ftw/events/testing.py
ftw/events/utils.py
ftw/events/vocabularies.py
ftw/events/behaviors/__init__.py
ftw/events/behaviors/configure.zcml
ftw/events/behaviors/location.py
ftw/events/behaviors/mopage.py
ftw/events/browser/__init__.py
ftw/events/browser/configure.zcml
ftw/events/browser/event_accessor.py
ftw/events/browser/eventlisting.py
ftw/events/browser/eventlistingblock.py
ftw/events/browser/mopage.py
ftw/events/browser/templates/eventlisting.pt
ftw/events/browser/templates/eventlistingblock.pt
ftw/events/browser/templates/events_rss.pt
ftw/events/browser/templates/mopage_events.pt
ftw/events/contents/__init__.py
ftw/events/contents/eventfolder.py
ftw/events/contents/eventlistingblock.py
ftw/events/contents/eventpage.py
ftw/events/locales/ftw.events.pot
ftw/events/locales/plone.pot
ftw/events/locales/de/LC_MESSAGES/ftw.events.po
ftw/events/locales/de/LC_MESSAGES/plone.po
ftw/events/portlets/__init__.py
ftw/events/portlets/configure.zcml
ftw/events/portlets/events_archive_portlet.py
ftw/events/portlets/templates/events_archive_portlet.pt
ftw/events/profiles/default/actions.xml
ftw/events/profiles/default/browserlayer.xml
ftw/events/profiles/default/jsregistry.xml
ftw/events/profiles/default/metadata.xml
ftw/events/profiles/default/portlets.xml
ftw/events/profiles/default/propertiestool.xml
ftw/events/profiles/default/rolemap.xml
ftw/events/profiles/default/tinymce.xml
ftw/events/profiles/default/types.xml
ftw/events/profiles/default/workflows.xml
ftw/events/profiles/default/types/Plone_Site.xml
ftw/events/profiles/default/types/ftw.events.EventFolder.xml
ftw/events/profiles/default/types/ftw.events.EventListingBlock.xml
