Metadata-Version: 2.1
Name: ftw.events
Version: 1.16.0
Summary: Events with simplelayout.
Home-page: https://github.com/4teamwork/ftw.events
Author: 4teamwork AG
Author-email: mailto:info@4teamwork.ch
License: GPL2
Keywords: ftw events
Platform: UNKNOWN
Classifier: Framework :: Plone
Classifier: Framework :: Plone :: 4.3
Classifier: Framework :: Plone :: 5.1
Classifier: License :: OSI Approved :: GNU General Public License (GPL)
Classifier: Programming Language :: Python
Classifier: Programming Language :: Python :: 2.7
Classifier: Topic :: Software Development :: Libraries :: Python Modules
Provides-Extra: development
Provides-Extra: tests
Provides-Extra: plone4
Provides-Extra: mopage_publisher_receiver
